{
    "First Name*": "Juuyou",
    "Last Name*": "Iyuhfg",
    "Email Address": "rrFZhT@mailinator.com",
    "Account Type*": "INDIVIDUAL",
    "Account Sub-Type*": "EMPLOYEE",
    "Address Type*": "Rural Route",
    "Street Address*": "PKIIkP",
    "State / Province*": "Nova Scotia              ",
    "City*": "Gjsdsd",
    "Zip Code*": 74646,
    "Question*": "What is your dream job?",
    "Answer*": "PhLOkdhZUqESldcxiLMs",
    "P.O. Box No*": 9706369375,
    "PIN*": 10000000,
    "Confirm PIN*": 10000000,
    "Rural Route & Box*": "dwohzi",
    "Region*": "APO/FPO                  ",
    "Address*": "stUNeI",
    "Post Office*": "Army Post Office",
    "Email Marketing Preferences*": "Do not send communications",
    "Device Number": "994493613614862",
    "SIM Number": "8901260475962235546F",
    "Submarket*": "Dallas",
    "Phone Number*": "214664-DALLAS-TX"
}